chouette_iot_client/__init__.py
chouette_iot_client/_chouette_client.py
chouette_iot_client/_storages.py
chouette_iot_client/_timed.py
chouette_iot_client/_timed_decorator.py
chouette_iot_client-0.0.1.dist-info/LICENSE
chouette_iot_client-0.0.1.dist-info/METADATA
chouette_iot_client-0.0.1.dist-info/WHEEL
chouette_iot_client-0.0.1.dist-info/top_level.txt
chouette_iot_client-0.0.1.dist-info/RECORD
