Metadata-Version: 2.1
Name: chouette-iot-client
Version: 0.0.1
Summary: Python Client for Chouette-IoT metrics collection agent
Home-page: https://github.com/akatashev/chouette-iot-client
Author: Artem Katashev
Author-email: aharr@rowanleaf.net
License: Apache License, Version 2.0
Platform: UNKNOWN
Classifier: Intended Audience :: Developers
Classifier: License :: OSI Approved :: Apache Software License
Classifier: Operating System :: OS Independent
Classifier: Programming Language :: Python :: 3
Classifier: Topic :: Software Development :: Libraries
Classifier: Topic :: System :: Monitoring
Requires-Python: >=3.6
Requires-Dist: redis
